src/pc.sv
module program_counter(
    input logic clk,
    input logic reset,
    input logic [31:0] next,
    output logic [31:0] pc
);

always_ff @(posedge clk) begin
    if(!reset) begin
        pc <= 32'h0;
    end
    else begin
        pc <= next;
    end
end

endmodule

tb/pc_tb.sv
`timescale 1ns/1ps

module program_counter_tb;

    // Testbench signals
    logic        clk;
    logic        rst_n;
    logic [31:0] pc_next;
    logic [31:0] pc;

    // Instantiate the Device Under Test (DUT)
    program_counter dut (
        .clk(clk),
        .reset(rst_n),
        .next(pc_next),
        .pc(pc)
    );

    // Clock generation (10ns period)
    always #5 clk = ~clk;

    // Test sequence
    initial begin
        // 1. Tell Icarus Verilog to dump waveforms into the sim folder
        $dumpfile("sim/dump.vcd");
        $dumpvars(0, program_counter_tb);

        // 2. Initialize signals and assert reset
        clk = 0;
        rst_n = 0;
        pc_next = 32'h00000000;

        // 3. Release reset after 10ns
        #10 rst_n = 1;

        // 4. Simulate standard sequential execution (PC + 4)
        #10 pc_next = 32'h00000004;
        #10 pc_next = 32'h00000008;
        #10 pc_next = 32'h0000000C;

        // 5. Simulate a branch or jump to a new address
        #10 pc_next = 32'h00000400;
        #10 pc_next = 32'h00000404;

        // End simulation
        #20 $finish;
    end

endmodule

sim/dump.vcd
$date
	Tue Jun 23 12:51:09 2026
$end
$version
	Icarus Verilog
$end
$timescale
	1ps
$end
$scope module program_counter_tb $end
$var wire 32 ! pc [31:0] $end
$var reg 1 " clk $end
$var reg 32 # pc_next [31:0] $end
$var reg 1 $ rst_n $end
$scope module dut $end
$var wire 1 " clk $end
$var wire 32 % next [31:0] $end
$var wire 1 $ reset $end
$var reg 32 & pc [31:0] $end
$upscope $end
$upscope $end
$enddefinitions $end
#0
$dumpvars
bx &
b0 %
0$
b0 #
0"
bx !
$end
#5000
b0 !
b0 &
1"
#10000
0"
1$
#15000
1"
#20000
0"
b100 #
b100 %
#25000
b100 !
b100 &
1"
#30000
0"
b1000 #
b1000 %
#35000
b1000 !
b1000 &
1"
#40000
0"
b1100 #
b1100 %
#45000
b1100 !
b1100 &
1"
#50000
0"
b10000000000 #
b10000000000 %
#55000
b10000000000 !
b10000000000 &
1"
#60000
0"
b10000000100 #
b10000000100 %
#65000
b10000000100 !
b10000000100 &
1"
